package_creation_tutorial/__init__.py
package_creation_tutorial/main.py
package_creation_tutorial/string_ops.py
package_creation_tutorial_kh-0.1.3.dist-info/METADATA
package_creation_tutorial_kh-0.1.3.dist-info/WHEEL
package_creation_tutorial_kh-0.1.3.dist-info/RECORD
